chainguard_pig_latin/__init__.py
chainguard_pig_latin/cli.py
chainguard_pig_latin/converter.py
chainguard_pig_latin/py.typed
chainguard_pig_latin-0.1.1.dist-info/licenses/LICENSE
chainguard_pig_latin-0.1.1.dist-info/METADATA
chainguard_pig_latin-0.1.1.dist-info/WHEEL
chainguard_pig_latin-0.1.1.dist-info/entry_points.txt
chainguard_pig_latin-0.1.1.dist-info/top_level.txt
chainguard_pig_latin-0.1.1.dist-info/RECORD
