Metadata-Version: 2.4
Name: chainguard-pig-latin
Version: 0.1.1
Summary: A Python package to convert text to Pig Latin - built from source for Chainguard
Author-email: Adam Lamorre <alamorre@users.noreply.github.com>
License: MIT
Project-URL: Homepage, https://github.com/alamorre/chainguard-pig-latin
Project-URL: Repository, https://github.com/alamorre/chainguard-pig-latin
Project-URL: Issues, https://github.com/alamorre/chainguard-pig-latin/issues
Keywords: pig-latin,text-processing,language,fun,chainguard
Classifier: Development Status :: 4 - Beta
Classifier: Intended Audience :: Developers
Classifier: License :: OSI Approved :: MIT License
Classifier: Programming Language :: Python :: 3
Classifier: Programming Language :: Python :: 3.8
Classifier: Programming Language :: Python :: 3.9
Classifier: Programming Language :: Python :: 3.10
Classifier: Programming Language :: Python :: 3.11
Classifier: Programming Language :: Python :: 3.12
Requires-Python: >=3.8
License-File: LICENSE
Dynamic: license-file
